fastzdp_api/__init__.py
fastzdp_api/api.py
fastzdp_api/crud_router.py
fastzdp_api/middleware_cors.py
fastzdp_api-0.1.6.dist-info/LICENSE
fastzdp_api-0.1.6.dist-info/METADATA
fastzdp_api-0.1.6.dist-info/WHEEL
fastzdp_api-0.1.6.dist-info/RECORD
