Metadata-Version: 2.1
Name: fastzdp-api
Version: 0.1.6
Summary: 
Author: 张大鹏
Author-email: 1156956636@qq.com
Requires-Python: >=3.7,<4.0
Classifier: Programming Language :: Python :: 3
Classifier: Programming Language :: Python :: 3.7
Classifier: Programming Language :: Python :: 3.8
Classifier: Programming Language :: Python :: 3.9
Classifier: Programming Language :: Python :: 3.10
Classifier: Programming Language :: Python :: 3.11
Classifier: Programming Language :: Python :: 3.12
Requires-Dist: fastapi (>=0.112.2,<0.113.0)
Requires-Dist: fastzdp-sqlmodel (>=0.1.4,<0.2.0)
Requires-Dist: uvicorn (>=0.30.6,<0.31.0)
